runigma/__init__.py
runigma/__main__.py
runigma/keyfile.py
runigma/machine.py
runigma/main.py
runigma/plugboard.py
runigma/sheet.py
runigma/rotors/__init__.py
runigma/rotors/data.py
runigma/rotors/factory.py
runigma/rotors/rotor.py
runigma/tests/__init__.py
runigma/tests/test_ruenigma.py
runigma-2019.3.data/scripts/runigma
runigma-2019.3.data/scripts/runigma-sheet
runigma-2019.3.dist-info/LICENSE
runigma-2019.3.dist-info/METADATA
runigma-2019.3.dist-info/WHEEL
runigma-2019.3.dist-info/top_level.txt
runigma-2019.3.dist-info/RECORD
